HISTORY.rst
MANIFEST.in
README.rst
setup.cfg
setup.py
fs.webdavfs.egg-info/PKG-INFO
fs.webdavfs.egg-info/SOURCES.txt
fs.webdavfs.egg-info/dependency_links.txt
fs.webdavfs.egg-info/entry_points.txt
fs.webdavfs.egg-info/requires.txt
fs.webdavfs.egg-info/top_level.txt
webdavfs/__init__.py
webdavfs/opener.py
webdavfs/webdavfs.py
webdavfs/tests/__init__.py
webdavfs/tests/base.py
webdavfs/tests/test_docker.py
webdavfs/tests/test_opener.py
webdavfs/tests/test_server.py