Metadata-Version: 1.1
Name: fs.webdavfs
Version: 0.4.3.1
Summary: WebDAV support for pyfilesystem2
Home-page: http://pypi.python.org/pypi/fs.webdavfs/
Author: Andreas Jung and others
Author-email: info@zopyx.com
License: MIT
Platform: any
Classifier: Development Status :: 5 - Production/Stable
Classifier: Intended Audience :: Developers
Classifier: License :: OSI Approved :: MIT License
Classifier: Operating System :: OS Independent
Classifier: Programming Language :: Python
Classifier: Programming Language :: Python :: 2.7
Classifier: Programming Language :: Python :: 3.5
Classifier: Programming Language :: Python :: 3.6
Classifier: Programming Language :: Python :: 3.7
Classifier: Topic :: System :: Filesystems
